{
    "type": "object",
    "properties": {
        "id": {
            "type": "integer",
            "description": "The ID of the Note"
        },
        "active_flag": {
            "type": "boolean",
            "description": "If Note is active or deleted"
        },
        "add_time": {
            "type": "string",
            "description": "The creation date and time of the Note"
        },
        "content": {
            "type": "string",
            "description": "Content of the Note in HTML format. Subject to sanitization on the back-end."
        },
        "deal": {
            "type": "object",
            "description": "The Deal this Note is attached to",
            "properties": {
                "title": {
                    "type": "string",
                    "description": "The title of the Deal this Note is attached to"
                }
            }
        },
        "lead_id": {
            "type": "string",
            "format": "uuid",
            "description": "The ID of the Lead the Note is attached to"
        },
        "deal_id": {
            "type": "integer",
            "description": "The ID of the Deal the Note is attached to"
        },
        "last_update_user_id": {
            "type": "integer",
            "description": "The ID of the User who updated the Note last"
        },
        "org_id": {
            "type": "integer",
            "description": "The ID of the Organization this Note is attached to"
        },
        "organization": {
            "type": "object",
            "description": "The Organization this Note is attached to",
            "properties": {
                "name": {
                    "type": "string",
                    "description": "The name of the Organization this Note is attached to"
                }
            }
        },
        "person": {
            "type": "object",
            "description": "The Person this Note is attached to",
            "properties": {
                "name": {
                    "type": "string",
                    "description": "The name of the Person this Note is attached to"
                }
            }
        },
        "person_id": {
            "type": "integer",
            "description": "The ID of the Person this Note is attached to"
        },
        "pinned_to_deal_flag": {
            "type": "boolean",
            "description": "If true, then the results are filtered by Note to Deal pinning state."
        },
        "pinned_to_organization_flag": {
            "type": "boolean",
            "description": "If true, then the results are filtered by Note to Organization pinning state."
        },
        "pinned_to_person_flag": {
            "type": "boolean",
            "description": "If true, then the results are filtered by Note to Person pinning state."
        },
        "update_time": {
            "type": "string",
            "description": "The last updated date and time of the Note"
        },
        "user": {
            "type": "object",
            "description": "The User who created the Note",
            "properties": {
                "email": {
                    "type": "string",
                    "description": "The Email of the Note creator"
                },
                "icon_url": {
                    "type": "string",
                    "description": "The URL of the Note creator avatar picture"
                },
                "is_you": {
                    "type": "boolean",
                    "description": "If the Note is created by you or not"
                },
                "name": {
                    "type": "string",
                    "description": "The name of the Note creator"
                }
            }
        },
        "user_id": {
            "type": "integer",
            "description": "The ID of the Note creator"
        }
    }
}